wagtail_resume/__init__.py
wagtail_resume/apps.py
wagtail_resume/blocks.py
wagtail_resume/locale/sv/LC_MESSAGES/django.po
wagtail_resume/migrations/0001_initial.py
wagtail_resume/migrations/0002_auto_20191227_0916.py
wagtail_resume/migrations/0003_auto_20200110_1525.py
wagtail_resume/migrations/0004_auto_20200110_1656.py
wagtail_resume/migrations/0005_auto_20200227_1224.py
wagtail_resume/migrations/0006_alter_baseresumepage_social_links.py
wagtail_resume/migrations/0007_baseresumepage_pdf_generation_visibility.py
wagtail_resume/migrations/0008_auto_20220211_1557.py
wagtail_resume/migrations/0009_alter_baseresumepage_pdf_generation_visibility.py
wagtail_resume/migrations/0010_alter_baseresumepage_resume_and_more.py
wagtail_resume/migrations/0011_baseresumepage_about_icon_and_more.py
wagtail_resume/migrations/0012_alter_baseresumepage_resume.py
wagtail_resume/migrations/0013_alter_baseresumepage_resume.py
wagtail_resume/migrations/0014_baseresumepage_display_last_update.py
wagtail_resume/migrations/__init__.py
wagtail_resume/models.py
wagtail_resume/static/wagtail_resume/css/.gitkeep
wagtail_resume/static/wagtail_resume/css/academic_resume_page.css
wagtail_resume/static/wagtail_resume/css/resume_page.css
wagtail_resume/static/wagtail_resume/images/.gitkeep
wagtail_resume/static/wagtail_resume/js/.gitkeep
wagtail_resume/templates/wagtail_resume/academic_resume_page.html
wagtail_resume/templates/wagtail_resume/blocks/contributions_block.html
wagtail_resume/templates/wagtail_resume/blocks/education_block.html
wagtail_resume/templates/wagtail_resume/blocks/work_experience_block.html
wagtail_resume/templates/wagtail_resume/blocks/writings_block.html
wagtail_resume/templates/wagtail_resume/localization_dropdown.html
wagtail_resume/templates/wagtail_resume/resume_page.html
wagtail_resume/templates/wagtail_resume/resume_page_body.html
wagtail_resume/templates/wagtail_resume/resume_page_head.html
wagtail_resume/templatetags/__init__.py
wagtail_resume-2.12.0.dist-info/LICENSE
wagtail_resume-2.12.0.dist-info/METADATA
wagtail_resume-2.12.0.dist-info/WHEEL
wagtail_resume-2.12.0.dist-info/RECORD
