Metadata-Version: 2.3
Name: wagtail-resume
Version: 2.12.0
Summary: A Wagtail project made to simplify creation of resumes for developers.
License: MIT
Keywords: Resume,Django,Wagtail,CMS
Author: Adin Hodovic
Author-email: hodovicadin@gmail.com
Requires-Python: >=3.10,<4.0
Classifier: Development Status :: 5 - Production/Stable
Classifier: Environment :: Web Environment
Classifier: Framework :: Django
Classifier: Framework :: Django :: 4.2
Classifier: Framework :: Django :: 5.0
Classifier: Framework :: Django :: 6.0
Classifier: Framework :: Wagtail
Classifier: Framework :: Wagtail :: 4
Classifier: Framework :: Wagtail :: 5
Classifier: Framework :: Wagtail :: 6
Classifier: Framework :: Wagtail :: 7
Classifier: Intended Audience :: Developers
Classifier: License :: OSI Approved :: MIT License
Classifier: Operating System :: OS Independent
Classifier: Programming Language :: Python
Classifier: Programming Language :: Python :: 3
Classifier: Programming Language :: Python :: 3.10
Classifier: Programming Language :: Python :: 3.11
Classifier: Programming Language :: Python :: 3.12
Classifier: Programming Language :: Python :: 3.13
Requires-Dist: Django (>=4.0.0,<7.0.0)
Requires-Dist: pymdown-extensions (>=10,<12)
Requires-Dist: wagtail (>=4.0.0,<8.0.0)
Requires-Dist: wagtail-markdown (>=0.10,<0.14)
Requires-Dist: wagtail-metadata (>=4.0.0,<6.0.0)
Requires-Dist: weasyprint (>=63,<=68)
Project-URL: Documentation, https://github.com/adinhodovic/wagtail-resume
Project-URL: Homepage, https://github.com/adinhodovic/wagtail-resume
Project-URL: Repository, https://github.com/adinhodovic/wagtail-resume
